{
  "total_runtime": 74.32095098495483,
  "total_near_misses": 19,
  "near_misses": [
    {
      "timestamp": 73.97512602806091,
      "distance": 49.95209513507771,
      "ship_position": [
        529.7460297961273,
        590
      ],
      "meteor_position": [
        496.5460173959991,
        552.6774734909976
      ],
      "ship_velocity": [
        -0.30494874416578144,
        4.99069196238675
      ],
      "meteor_velocity": [
        0.9717143197573443,
        0.23615943931700364
      ],
      "severity": "WARNING"
    },
    {
      "timestamp": 73.991614818573,
      "distance": 48.947046617508455,
      "ship_position": [
        529.4616630666266,
        590
      ],
      "meteor_position": [
        497.51773171575644,
        552.9136329303146
      ],
      "ship_velocity": [
        -0.2843667295007823,
        4.991907006661185
      ],
      "meteor_velocity": [
        0.9717143197573443,
        0.23615943931700364
      ],
      "severity": "WARNING"
    },
    {
      "timestamp": 74.00851082801819,
      "distance": 47.96740941963268,
      "ship_position": [
        529.1966856384056,
        590
      ],
      "meteor_position": [
        498.48944603551377,
        553.1497923696317
      ],
      "ship_velocity": [
        -0.2649774282209163,
        4.992973759447713
      ],
      "meteor_velocity": [
        0.9717143197573443,
        0.23615943931700364
      ],
      "severity": "WARNING"
    },
    {
      "timestamp": 74.02612495422363,
      "distance": 47.01259090876535,
      "ship_position": [
        528.9500596059772,
        590
      ],
      "meteor_position": [
        499.4611603552711,
        553.3859518089487
      ],
      "ship_velocity": [
        -0.24662603242832856,
        4.993913855897863
      ],
      "meteor_velocity": [
        0.9717143197573443,
        0.23615943931700364
      ],
      "severity": "WARNING"
    },
    {
      "timestamp": 74.04255986213684,
      "distance": 46.08212527540324,
      "ship_position": [
        528.720884146612,
        590
      ],
      "meteor_position": [
        500.4328746750284,
        553.6221112482657
      ],
      "ship_velocity": [
        -0.22917545936528722,
        4.994745099484528
      ],
      "meteor_velocity": [
        0.9717143197573443,
        0.23615943931700364
      ],
      "severity": "WARNING"
    },
    {
      "timestamp": 74.06033492088318,
      "distance": 45.17565772869631,
      "ship_position": [
        528.5083793852141,
        590
      ],
      "meteor_position": [
        501.40458899478574,
        553.8582706875827
      ],
      "ship_velocity": [
        -0.21250476139792185,
        4.995482131524765
      ],
      "meteor_velocity": [
        0.9717143197573443,
        0.23615943931700364
      ],
      "severity": "WARNING"
    },
    {
      "timestamp": 74.0768051147461,
      "distance": 44.29293007077025,
      "ship_position": [
        528.3118716781255,
        590
      ],
      "meteor_position": [
        502.37630331454307,
        554.0944301268997
      ],
      "ship_velocity": [
        -0.1965077070885568,
        4.9961369798129835
      ],
      "meteor_velocity": [
        0.9717143197573443,
        0.23615943931700364
      ],
      "severity": "WARNING"
    },
    {
      "timestamp": 74.09415006637573,
      "distance": 43.43376749666582,
      "ship_position": [
        528.130780157085,
        590
      ],
      "meteor_position": [
        503.3480176343004,
        554.3305895662168
      ],
      "ship_velocity": [
        -0.18109152104042714,
        4.996719509939223
      ],
      "meteor_velocity": [
        0.9717143197573443,
        0.23615943931700364
      ],
      "severity": "WARNING"
    },
    {
      "timestamp": 74.1109607219696,
      "distance": 42.598066486651376,
      "ship_position": [
        527.9646043868777,
        590
      ],
      "meteor_position": [
        504.3197319540577,
        554.5667490055338
      ],
      "ship_velocity": [
        -0.1661757702073719,
        4.997237798363811
      ],
      "meteor_velocity": [
        0.9717143197573443,
        0.23615943931700364
      ],
      "severity": "WARNING"
    },
    {
      "timestamp": 74.12776899337769,
      "distance": 41.785783677537935,
      "ship_position": [
        527.8129130023485,
        590
      ],
      "meteor_position": [
        505.29144627381504,
        554.8029084448508
      ],
      "ship_velocity": [
        -0.1516913845292053,
        4.997698442669347
      ],
      "meteor_velocity": [
        0.9717143197573443,
        0.23615943931700364
      ],
      "severity": "WARNING"
    },
    {
      "timestamp": 74.14471077919006,
      "distance": 40.99692561931943,
      "ship_position": [
        527.6753332023522,
        590
      ],
      "meteor_position": [
        506.26316059357237,
        555.0390678841678
      ],
      "ship_velocity": [
        -0.13757979999626674,
        4.998106821450797
      ],
      "meteor_velocity": [
        0.9717143197573443,
        0.23615943931700364
      ],
      "severity": "WARNING"
    },
    {
      "timestamp": 74.16267395019531,
      "distance": 40.23153934291205,
      "ship_position": [
        527.551540989845,
        590
      ],
      "meteor_position": [
        507.2348749133297,
        555.2752273234848
      ],
      "ship_velocity": [
        -0.12379221250727249,
        4.998467313899587
      ],
      "meteor_velocity": [
        0.9717143197573443,
        0.23615943931700364
      ],
      "severity": "WARNING"
    },
    {
      "timestamp": 74.17934489250183,
      "distance": 39.48970368388096,
      "ship_position": [
        527.4412520587173,
        590
      ],
      "meteor_position": [
        508.206589233087,
        555.5113867628019
      ],
      "ship_velocity": [
        -0.11028893112773193,
        4.998783487176725
      ],
      "meteor_velocity": [
        0.9717143197573443,
        0.23615943931700364
      ],
      "severity": "WARNING"
    },
    {
      "timestamp": 74.19680786132812,
      "distance": 38.77152132567303,
      "ship_position": [
        527.3442132391534,
        590
      ],
      "meteor_position": [
        509.17830355284434,
        555.7475462021189
      ],
      "ship_velocity": [
        -0.09703881956381671,
        4.999058258061978
      ],
      "meteor_velocity": [
        0.9717143197573443,
        0.23615943931700364
      ],
      "severity": "WARNING"
    },
    {
      "timestamp": 74.21387100219727,
      "distance": 38.07711154380551,
      "ship_position": [
        527.2601944243187,
        590
      ],
      "meteor_position": [
        510.15001787260167,
        555.9837056414359
      ],
      "ship_velocity": [
        -0.08401881483471815,
        4.999294034036582
      ],
      "meteor_velocity": [
        0.9717143197573443,
        0.23615943931700364
      ],
      "severity": "WARNING"
    },
    {
      "timestamp": 74.23144173622131,
      "distance": 37.40660364939769,
      "ship_position": [
        527.1889809120557,
        590
      ],
      "meteor_position": [
        511.121732192359,
        556.2198650807529
      ],
      "ship_velocity": [
        -0.07121351226295346,
        4.999492837845772
      ],
      "meteor_velocity": [
        0.9717143197573443,
        0.23615943931700364
      ],
      "severity": "WARNING"
    },
    {
      "timestamp": 74.24902486801147,
      "distance": 36.760131146012284,
      "ship_position": [
        527.1303661060316,
        590
      ],
      "meteor_position": [
        512.0934465121163,
        556.45602452007
      ],
      "ship_velocity": [
        -0.058614806024147106,
        4.99965641864666
      ],
      "meteor_velocity": [
        0.9717143197573443,
        0.23615943931700364
      ],
      "severity": "WARNING"
    },
    {
      "timestamp": 74.26570177078247,
      "distance": 36.1378266275511,
      "ship_position": [
        527.0841445314013,
        590
      ],
      "meteor_position": [
        513.0651608318736,
        556.692183959387
      ],
      "ship_velocity": [
        -0.04622157463029391,
        4.999786352039324
      ],
      "meteor_velocity": [
        0.9717143197573443,
        0.23615943931700364
      ],
      "severity": "WARNING"
    },
    {
      "timestamp": 74.28245091438293,
      "distance": 35.53981745644153,
      "ship_position": [
        527.0501051305079,
        590
      ],
      "meteor_position": [
        514.036875151631,
        556.928343398704
      ],
      "ship_velocity": [
        -0.03403940089339276,
        4.99988413057611
      ],
      "meteor_velocity": [
        0.9717143197573443,
        0.23615943931700364
      ],
      "severity": "WARNING"
    }
  ]
}